LICENSE
MANIFEST.in
README.rst
setup.cfg
setup.py
src/ctds/__init__.py
src/ctds/connection.c
src/ctds/cursor.c
src/ctds/parameter.c
src/ctds/pyutils.c
src/ctds/tds.c
src/ctds/type.c
src/ctds.egg-info/PKG-INFO
src/ctds.egg-info/SOURCES.txt
src/ctds.egg-info/dependency_links.txt
src/ctds.egg-info/entry_points.txt
src/ctds.egg-info/not-zip-safe
src/ctds.egg-info/requires.txt
src/ctds.egg-info/top_level.txt
src/ctds/include/c99bool.h
src/ctds/include/c99int.h
src/ctds/include/connection.h
src/ctds/include/cursor.h
src/ctds/include/macros.h
src/ctds/include/parameter.h
src/ctds/include/pop_warnings.h
src/ctds/include/push_warnings.h
src/ctds/include/pyutils.h
src/ctds/include/tds.h
src/ctds/include/type.h
src/ctds/pool/__init__.py